ttt/__init__.py
pyttt-0.5.4.dist-info/LICENSE
pyttt-0.5.4.dist-info/METADATA
pyttt-0.5.4.dist-info/WHEEL
pyttt-0.5.4.dist-info/top_level.txt
pyttt-0.5.4.dist-info/RECORD
