Metadata-Version: 2.1
Name: pyttt
Version: 0.5.4
Summary: Multi Player Tic Tac Toe Game
Home-page: https://github.com/CKVB/Tic-Tac-Toe/blob/master/ttt.py
Author: Chaitanya Krishna VB
Author-email: python7460@gmail.com
License: MIT LICENSE
Platform: UNKNOWN
Classifier: Programming Language :: Python :: 3
Classifier: License :: OSI Approved :: MIT License
Classifier: Operating System :: OS Independent
